telget/Username.py
telget/__init__.py
telget-1.0.0.dist-info/LICENSE
telget-1.0.0.dist-info/METADATA
telget-1.0.0.dist-info/WHEEL
telget-1.0.0.dist-info/top_level.txt
telget-1.0.0.dist-info/RECORD
