Metadata-Version: 2.1
Name: telget
Version: 1.0.0
Summary: a Small Library for Getting Info About Telegram Usernames .
Home-page: https://github.com/mrpythonblog/telget
Author: MrPythonBlog
Author-email: mrpython@gmail.com
License: UNKNOWN
Platform: UNKNOWN
Classifier: Programming Language :: Python :: 3
Classifier: License :: OSI Approved :: MIT License
Classifier: Operating System :: OS Independent
Requires-Python: >=3.5
